<annotation>
	<folder>Images</folder>
	<filename>image-69.jpg</filename>
	<path>D:\AutomateDriving\Images\image-69.jpg</path>
	<source>
		<database>Unknown</database>
	</source>
	<size>
		<width>800</width>
		<height>600</height>
		<depth>3</depth>
	</size>
	<segmented>0</segmented>
	<object>
		<name>pole</name>
		<pose>Unspecified</pose>
		<truncated>0</truncated>
		<difficult>0</difficult>
		<bndbox>
			<xmin>518</xmin>
			<ymin>160</ymin>
			<xmax>537</xmax>
			<ymax>369</ymax>
		</bndbox>
	</object>
	<object>
		<name>pole</name>
		<pose>Unspecified</pose>
		<truncated>0</truncated>
		<difficult>0</difficult>
		<bndbox>
			<xmin>279</xmin>
			<ymin>239</ymin>
			<xmax>293</xmax>
			<ymax>359</ymax>
		</bndbox>
	</object>
	<object>
		<name>pole</name>
		<pose>Unspecified</pose>
		<truncated>0</truncated>
		<difficult>0</difficult>
		<bndbox>
			<xmin>454</xmin>
			<ymin>259</ymin>
			<xmax>462</xmax>
			<ymax>355</ymax>
		</bndbox>
	</object>
	<object>
		<name>person</name>
		<pose>Unspecified</pose>
		<truncated>0</truncated>
		<difficult>0</difficult>
		<bndbox>
			<xmin>136</xmin>
			<ymin>321</ymin>
			<xmax>159</xmax>
			<ymax>377</ymax>
		</bndbox>
	</object>
	<object>
		<name>person</name>
		<pose>Unspecified</pose>
		<truncated>0</truncated>
		<difficult>0</difficult>
		<bndbox>
			<xmin>498</xmin>
			<ymin>320</ymin>
			<xmax>515</xmax>
			<ymax>355</ymax>
		</bndbox>
	</object>
	<object>
		<name>person</name>
		<pose>Unspecified</pose>
		<truncated>0</truncated>
		<difficult>0</difficult>
		<bndbox>
			<xmin>468</xmin>
			<ymin>324</ymin>
			<xmax>477</xmax>
			<ymax>352</ymax>
		</bndbox>
	</object>
	<object>
		<name>vehicle</name>
		<pose>Unspecified</pose>
		<truncated>0</truncated>
		<difficult>0</difficult>
		<bndbox>
			<xmin>378</xmin>
			<ymin>332</ymin>
			<xmax>393</xmax>
			<ymax>344</ymax>
		</bndbox>
	</object>
</annotation>
